msg_topgen/__init__.py
msg_topgen/__main__.py
msg_topgen/arg_parser.py
msg_topgen/generate.py
msg_topgen/msg_topgen.py
msg_topgen/topology.py
msg_topgen-0.1.14.dist-info/DESCRIPTION.rst
msg_topgen-0.1.14.dist-info/METADATA
msg_topgen-0.1.14.dist-info/RECORD
msg_topgen-0.1.14.dist-info/WHEEL
msg_topgen-0.1.14.dist-info/entry_points.txt
msg_topgen-0.1.14.dist-info/metadata.json
msg_topgen-0.1.14.dist-info/top_level.txt
