Metadata-Version: 2.0
Name: msg-topgen
Version: 0.1.14
Summary: UNKNOWN
Home-page: https://github.com/rh-messaging-qe/qpid_generator
Author: Dominik Lenoch <dlenoch@redhat.com>, Jakub Stejskal <jstejska@redhat.com>
Author-email: jstejska@redhat.com
License: Apache 2.0
Platform: UNKNOWN
Requires-Dist: networkx (==2.0)
Requires-Dist: PyYAML (>=3.12)
Requires-Dist: ansible (>=2.3.2.0)
Requires-Dist: libracmp
Requires-Dist: matplotlib
Requires-Dist: argparse
